Metadata-Version: 2.1
Name: odoo12-addon-website-no-crawler
Version: 12.0.1.2.0
Summary: Disables robots.txt for indexing by webcrawlers like Google
Home-page: https://github.com/OCA/website
Author: B-Informed B.V.,Odoo Community Association (OCA)
Author-email: support@odoo-community.org
License: AGPL-3
Platform: UNKNOWN
Classifier: Programming Language :: Python
Classifier: Framework :: Odoo
Classifier: License :: OSI Approved :: GNU Affero General Public License v3
Requires-Python: >=3.5
Requires-Dist: odoo (<12.1dev,>=12.0a)
